{
  "resource_type": "azurerm_public_ip",
  "version": 0,
  "block": {
    "attributes": {
      "allocation_method": {
        "type": "string",
        "required": true,
        "optional": false,
        "computed": false,
        "sensitive": false,
        "description": ""
      },
      "ddos_protection_mode": {
        "type": "string",
        "required": false,
        "optional": true,
        "computed": false,
        "sensitive": false,
        "description": ""
      },
      "ddos_protection_plan_id": {
        "type": "string",
        "required": false,
        "optional": true,
        "computed": false,
        "sensitive": false,
        "description": ""
      },
      "domain_name_label": {
        "type": "string",
        "required": false,
        "optional": true,
        "computed": false,
        "sensitive": false,
        "description": ""
      },
      "edge_zone": {
        "type": "string",
        "required": false,
        "optional": true,
        "computed": false,
        "sensitive": false,
        "description": ""
      },
      "id": {
        "type": "string",
        "required": false,
        "optional": true,
        "computed": true,
        "sensitive": false,
        "description": ""
      },
      "idle_timeout_in_minutes": {
        "type": "number",
        "required": false,
        "optional": true,
        "computed": false,
        "sensitive": false,
        "description": ""
      },
      "ip_tags": {
        "type": [
          "map",
          "string"
        ],
        "required": false,
        "optional": true,
        "computed": false,
        "sensitive": false,
        "description": ""
      },
      "ip_version": {
        "type": "string",
        "required": false,
        "optional": true,
        "computed": false,
        "sensitive": false,
        "description": ""
      },
      "location": {
        "type": "string",
        "required": true,
        "optional": false,
        "computed": false,
        "sensitive": false,
        "description": ""
      },
      "name": {
        "type": "string",
        "required": true,
        "optional": false,
        "computed": false,
        "sensitive": false,
        "description": ""
      },
      "public_ip_prefix_id": {
        "type": "string",
        "required": false,
        "optional": true,
        "computed": false,
        "sensitive": false,
        "description": ""
      },
      "resource_group_name": {
        "type": "string",
        "required": true,
        "optional": false,
        "computed": false,
        "sensitive": false,
        "description": ""
      },
      "reverse_fqdn": {
        "type": "string",
        "required": false,
        "optional": true,
        "computed": false,
        "sensitive": false,
        "description": ""
      },
      "sku": {
        "type": "string",
        "required": false,
        "optional": true,
        "computed": false,
        "sensitive": false,
        "description": ""
      },
      "sku_tier": {
        "type": "string",
        "required": false,
        "optional": true,
        "computed": false,
        "sensitive": false,
        "description": ""
      },
      "tags": {
        "type": [
          "map",
          "string"
        ],
        "required": false,
        "optional": true,
        "computed": false,
        "sensitive": false,
        "description": ""
      },
      "zones": {
        "type": [
          "set",
          "string"
        ],
        "required": false,
        "optional": true,
        "computed": false,
        "sensitive": false,
        "description": ""
      }
    },
    "block_types": {
      "timeouts": {
        "nesting_mode": "single",
        "min_items": 0,
        "max_items": 0,
        "block": {
          "attributes": {
            "create": {
              "type": "string",
              "required": false,
              "optional": true,
              "computed": false,
              "sensitive": false,
              "description": ""
            },
            "delete": {
              "type": "string",
              "required": false,
              "optional": true,
              "computed": false,
              "sensitive": false,
              "description": ""
            },
            "read": {
              "type": "string",
              "required": false,
              "optional": true,
              "computed": false,
              "sensitive": false,
              "description": ""
            },
            "update": {
              "type": "string",
              "required": false,
              "optional": true,
              "computed": false,
              "sensitive": false,
              "description": ""
            }
          },
          "block_types": {}
        }
      }
    }
  }
}